secretstore/__init__.py
secretstore/module.py
secretstore/session.py
secretstore/utils.py
secretstore-0.0.2.dist-info/LICENSE
secretstore-0.0.2.dist-info/METADATA
secretstore-0.0.2.dist-info/WHEEL
secretstore-0.0.2.dist-info/top_level.txt
secretstore-0.0.2.dist-info/RECORD
