Metadata-Version: 2.1
Name: secretstore
Version: 0.0.2
Summary: Python package for Parity's Secret Store API calls and sessions.
Home-page: https://github.com/energywebfoundation/secretstore-py
Author: Adam Nagy
Author-email: adam.nagy@energyweb.org
License: MIT
Project-URL: Documentation, https://secretstore.readthedocs.io/
Keywords: secretstore secret store parity api energyweb ewf
Platform: UNKNOWN
Classifier: Programming Language :: Python :: 3
Classifier: License :: OSI Approved :: MIT License
Classifier: Operating System :: OS Independent
Requires-Python: >=3.5.3,<4
Requires-Dist: web3 (>=4.0.0)
Requires-Dist: requests (<3.0.0,>=2.16.0)
Requires-Dist: decorator
Provides-Extra: dev
Requires-Dist: Sphinx; extra == 'dev'
Requires-Dist: sphinx-rtd-theme; extra == 'dev'
Requires-Dist: bumpversion; extra == 'dev'
Requires-Dist: setuptools (>=36.2.0); extra == 'dev'
Requires-Dist: wheel; extra == 'dev'
Provides-Extra: docs
Requires-Dist: Sphinx; extra == 'docs'
Requires-Dist: sphinx-rtd-theme; extra == 'docs'
